tlseparation/__init__.py
tlseparation/classification/__init__.py
tlseparation/classification/classes_reference.py
tlseparation/classification/classify_wood.py
tlseparation/classification/gmm.py
tlseparation/classification/path_detection.py
tlseparation/classification/point_features.py
tlseparation/classification/wlseparation.py
tlseparation/scripts/__init__.py
tlseparation/scripts/automated_separation.py
tlseparation/scripts/post_processing.py
tlseparation/utility/__init__.py
tlseparation/utility/cloud_analysis.py
tlseparation/utility/clustering.py
tlseparation/utility/data_utils.py
tlseparation/utility/downsampling.py
tlseparation/utility/filtering.py
tlseparation/utility/knnsearch.py
tlseparation/utility/peakdetect.py
tlseparation/utility/shortpath.py
tlseparation/utility/voxels.py
tlseparation-1.3.2.dist-info/METADATA
tlseparation-1.3.2.dist-info/RECORD
tlseparation-1.3.2.dist-info/WHEEL
tlseparation-1.3.2.dist-info/top_level.txt
