Metadata-Version: 2.1
Name: tlseparation
Version: 1.3.2
Summary: Performs the wood/leaf separation from 3D point clouds generated using Terrestrial LiDAR Scanners.
Home-page: https://github.com/TLSeparation/source
Author: Matheus Boni Vicari
Author-email: matheus.boni.vicari@gmail.com
License: LICENSE.txt
Keywords: wood/leaf separation TLS point cloud LiDAR
Platform: UNKNOWN
Classifier: Programming Language :: Python
Classifier: Topic :: Scientific/Engineering
Requires-Dist: scipy (>=0.19.0)
Requires-Dist: pandas (>=0.19.2)
Requires-Dist: numpy (>=1.11.3)
Requires-Dist: networkx (>=1.11)
Requires-Dist: scikit-learn (>=0.19.1)
